pcaplib/__init__.py
pcaplib-1.0.0.dist-info/DESCRIPTION.rst
pcaplib-1.0.0.dist-info/METADATA
pcaplib-1.0.0.dist-info/RECORD
pcaplib-1.0.0.dist-info/WHEEL
pcaplib-1.0.0.dist-info/metadata.json
pcaplib-1.0.0.dist-info/top_level.txt
