Metadata-Version: 2.0
Name: pcaplib
Version: 1.0.0
Summary: A very simple PCAP library
Home-page: UNKNOWN
Author: Salah Gherdaoui
Author-email: salah.gherdaoui@gmail.com
License: MIT License
